fourFuncCalc/sram256x8.v
// sram256x8
//
// Description:
//    Verilog representation of a 256x8 sram
//
// Inputs:
//    add[7:0] - 8 bit address
//    nOe - active low output enable 
//    nWe - 
//
// In / Out:
//    data[7:0] - 8 bit data
//		
// Authors: Scott Ogilvie
// Date:

module sram256x8(data, add, nCs, nOe, nWe);
    inout [7:0] data;
    input [7:0] add;
    input nCs;          // Chip Select active low
    input nOe;          // Output Enable active low
    input nWe;          // Write Enable active low
    reg [7:0] mem [0:255];  // Address, data

    assign data = (~nOe & ~nCs) ? mem[add] : 8'bZ;

	always @(posedge nWe) begin
		if (~nCs)
        mem[add] = data;
    end
	
endmodule

fourFuncCalc/sram256x8TestBench.v
// sram256x8TestBench.v
//
// Description:
// Test bench
//
// Inputs:
// Outputs:
//    mySram256x8.vcd
//    vars from mySram256x8
//    Displays add, data, nOe, nWe, time
//
// Authors: Scott Ogilvie
// Date:

//`include "sram256x8.v"
module testBench;
    //  connect the two modules
    wire [7:0] data;
    wire [7:0] add;     // Address
    wire nCs;           // Chip select active low
    wire nOe;           // Output enable active low
    wire nWe;           // Write enable active low

    sram256x8 mySram256x8(data, add, nCs, nOe, nWe);
    tester aTester (data, add, nCs, nOe, nWe);

    initial             // For gtkwave
    begin
        $dumpfile("mySram256x8.vcd");
        $dumpvars(1, mySram256x8);
    end
endmodule

module tester (data, add, nCs, nOe, nWe);
    inout [7:0] data;
    output [7:0] add;   // Address
    output nCs;         // Chip Select active low
    output nOe;         // Output Enable active low
    output nWe;         // Write Enable active low
    reg [7:0] ldata;
    reg [7:0] add;
    reg nCs;
    reg nOe;
    reg nWe;

    reg [8:0] index;    // Counters 1 bigger than address
    reg [7:0] value;    // Used for data
                        // so that for loop will exit
    assign data = (nOe | nCs) ? ldata : 8'bZ ;

    parameter STIMDELAY = 5;
    parameter SIMTIME = 256;
    parameter MAXADDR = 8'hFF;
    parameter MINADDR = 8'h00;
    parameter MAXDATA = 8'hFF;
    parameter MINDATA = 8'h00;

    initial             // Response
    begin
        $display("\t add \t ldata \t nCs \t nOe \t nWe \t\t Time \n");
        $monitor("\t %x \t %x \t %b \t %b \t %b \t %d\n", add, data,
            nCs, nOe, nWe, $time);
    end

    initial             // Stimulus
    begin

        value= 8'hFF;
        #STIMDELAY nCs = 1'b1;
        #STIMDELAY nCs = 1'b0;

        for (index = MINADDR; index<=MAXADDR; index = index + 9'h01)
        begin           // Fill add[0] with 127 to add[127] with 0
            nOe = 1'b1;
            nWe = 1'b1;
            #STIMDELAY add = index[7:0];
            #STIMDELAY ldata = value;
            #STIMDELAY nWe = 1'b0;
            #STIMDELAY nWe = 1'b1;
            value = value - 8'h01;
        end

        value= 8'hFF;
        for (index = MINADDR; index<=MAXADDR; index = index + 9'h01)
        begin           // Read add[0] with 127 to add[127]
            nWe = 1'b1;
            nOe = 1'b0;
            #STIMDELAY add = index[7:0];
            #(STIMDELAY*2);
            // Test data value here
            if (data != value)
            begin
                $display("Error: data: %h != expected %h at time %d\n",
                    data, value, $time);
            end
            #STIMDELAY nOe = 1'b1;
            #STIMDELAY;
            value = value - 8'h01;
        end

        #(SIMTIME*STIMDELAY+4*STIMDELAY);   // needed to see END of simulation
        $finish;                            // finish simulation
    end
endmodule

fourFuncCalc/mySram256x8.vcd
$date
	Mon Oct 26 23:48:13 2015
$end
$version
	Icarus Verilog
$end
$timescale
	1s
$end
$scope module testBench $end
$scope module mySram256x8 $end
$var wire 8 ! add [7:0] $end
$var wire 8 " data [7:0] $end
$var wire 1 # nCs $end
$var wire 1 $ nOe $end
$var wire 1 % nWe $end
$upscope $end
$upscope $end
$enddefinitions $end
#0
$dumpvars
x%
x$
x#
bx "
bx !
$end
#5
1#
#10
1%
1$
0#
#15
b0 !
#20
b11111111 "
#25
0%
#30
1%
#35
b1 !
#40
b11111110 "
#45
0%
#50
1%
#55
b10 !
#60
b11111101 "
#65
0%
#70
1%
#75
b11 !
#80
b11111100 "
#85
0%
#90
1%
#95
b100 !
#100
b11111011 "
#105
0%
#110
1%
#115
b101 !
#120
b11111010 "
#125
0%
#130
1%
#135
b110 !
#140
b11111001 "
#145
0%
#150
1%
#155
b111 !
#160
b11111000 "
#165
0%
#170
1%
#175
b1000 !
#180
b11110111 "
#185
0%
#190
1%
#195
b1001 !
#200
b11110110 "
#205
0%
#210
1%
#215
b1010 !
#220
b11110101 "
#225
0%
#230
1%
#235
b1011 !
#240
b11110100 "
#245
0%
#250
1%
#255
b1100 !
#260
b11110011 "
#265
0%
#270
1%
#275
b1101 !
#280
b11110010 "
#285
0%
#290
1%
#295
b1110 !
#300
b11110001 "
#305
0%
#310
1%
#315
b1111 !
#320
b11110000 "
#325
0%
#330
1%
#335
b10000 !
#340
b11101111 "
#345
0%
#350
1%
#355
b10001 !
#360
b11101110 "
#365
0%
#370
1%
#375
b10010 !
#380
b11101101 "
#385
0%
#390
1%
#395
b10011 !
#400
b11101100 "
#405
0%
#410
1%
#415
b10100 !
#420
b11101011 "
#425
0%
#430
1%
#435
b10101 !
#440
b11101010 "
#445
0%
#450
1%
#455
b10110 !
#460
b11101001 "
#465
0%
#470
1%
#475
b10111 !
#480
b11101000 "
#485
0%
#490
1%
#495
b11000 !
#500
b11100111 "
#505
0%
#510
1%
#515
b11001 !
#520
b11100110 "
#525
0%
#530
1%
#535
b11010 !
#540
b11100101 "
#545
0%
#550
1%
#555
b11011 !
#560
b11100100 "
#565
0%
#570
1%
#575
b11100 !
#580
b11100011 "
#585
0%
#590
1%
#595
b11101 !
#600
b11100010 "
#605
0%
#610
1%
#615
b11110 !
#620
b11100001 "
#625
0%
#630
1%
#635
b11111 !
#640
b11100000 "
#645
0%
#650
1%
#655
b100000 !
#660
b11011111 "
#665
0%
#670
1%
#675
b100001 !
#680
b11011110 "
#685
0%
#690
1%
#695
b100010 !
#700
b11011101 "
#705
0%
#710
1%
#715
b100011 !
#720
b11011100 "
#725
0%
#730
1%
#735
b100100 !
#740
b11011011 "
#745
0%
#750
1%
#755
b100101 !
#760
b11011010 "
#765
0%
#770
1%
#775
b100110 !
#780
b11011001 "
#785
0%
#790
1%
#795
b100111 !
#800
b11011000 "
#805
0%
#810
1%
#815
b101000 !
#820
b11010111 "
#825
0%
#830
1%
#835
b101001 !
#840
b11010110 "
#845
0%
#850
1%
#855
b101010 !
#860
b11010101 "
#865
0%
#870
1%
#875
b101011 !
#880
b11010100 "
#885
0%
#890
1%
#895
b101100 !
#900
b11010011 "
#905
0%
#910
1%
#915
b101101 !
#920
b11010010 "
#925
0%
#930
1%
#935
b101110 !
#940
b11010001 "
#945
0%
#950
1%
#955
b101111 !
#960
b11010000 "
#965
0%
#970
1%
#975
b110000 !
#980
b11001111 "
#985
0%
#990
1%
#995
b110001 !
#1000
b11001110 "
#1005
0%
#1010
1%
#1015
b110010 !
#1020
b11001101 "
#1025
0%
#1030
1%
#1035
b110011 !
#1040
b11001100 "
#1045
0%
#1050
1%
#1055
b110100 !
#1060
b11001011 "
#1065
0%
#1070
1%
#1075
b110101 !
#1080
b11001010 "
#1085
0%
#1090
1%
#1095
b110110 !
#1100
b11001001 "
#1105
0%
#1110
1%
#1115
b110111 !
#1120
b11001000 "
#1125
0%
#1130
1%
#1135
b111000 !
#1140
b11000111 "
#1145
0%
#1150
1%
#1155
b111001 !
#1160
b11000110 "
#1165
0%
#1170
1%
#1175
b111010 !
#1180
b11000101 "
#1185
0%
#1190
1%
#1195
b111011 !
#1200
b11000100 "
#1205
0%
#1210
1%
#1215
b111100 !
#1220
b11000011 "
#1225
0%
#1230
1%
#1235
b111101 !
#1240
b11000010 "
#1245
0%
#1250
1%
#1255
b111110 !
#1260
b11000001 "
#1265
0%
#1270
1%
#1275
b111111 !
#1280
b11000000 "
#1285
0%
#1290
1%
#1295
b1000000 !
#1300
b10111111 "
#1305
0%
#1310
1%
#1315
b1000001 !
#1320
b10111110 "
#1325
0%
#1330
1%
#1335
b1000010 !
#1340
b10111101 "
#1345
0%
#1350
1%
#1355
b1000011 !
#1360
b10111100 "
#1365
0%
#1370
1%
#1375
b1000100 !
#1380
b10111011 "
#1385
0%
#1390
1%
#1395
b1000101 !
#1400
b10111010 "
#1405
0%
#1410
1%
#1415
b1000110 !
#1420
b10111001 "
#1425
0%
#1430
1%
#1435
b1000111 !
#1440
b10111000 "
#1445
0%
#1450
1%
#1455
b1001000 !
#1460
b10110111 "
#1465
0%
#1470
1%
#1475
b1001001 !
#1480
b10110110 "
#1485
0%
#1490
1%
#1495
b1001010 !
#1500
b10110101 "
#1505
0%
#1510
1%
#1515
b1001011 !
#1520
b10110100 "
#1525
0%
#1530
1%
#1535
b1001100 !
#1540
b10110011 "
#1545
0%
#1550
1%
#1555
b1001101 !
#1560
b10110010 "
#1565
0%
#1570
1%
#1575
b1001110 !
#1580
b10110001 "
#1585
0%
#1590
1%
#1595
b1001111 !
#1600
b10110000 "
#1605
0%
#1610
1%
#1615
b1010000 !
#1620
b10101111 "
#1625
0%
#1630
1%
#1635
b1010001 !
#1640
b10101110 "
#1645
0%
#1650
1%
#1655
b1010010 !
#1660
b10101101 "
#1665
0%
#1670
1%
#1675
b1010011 !
#1680
b10101100 "
#1685
0%
#1690
1%
#1695
b1010100 !
#1700
b10101011 "
#1705
0%
#1710
1%
#1715
b1010101 !
#1720
b10101010 "
#1725
0%
#1730
1%
#1735
b1010110 !
#1740
b10101001 "
#1745
0%
#1750
1%
#1755
b1010111 !
#1760
b10101000 "
#1765
0%
#1770
1%
#1775
b1011000 !
#1780
b10100111 "
#1785
0%
#1790
1%
#1795
b1011001 !
#1800
b10100110 "
#1805
0%
#1810
1%
#1815
b1011010 !
#1820
b10100101 "
#1825
0%
#1830
1%
#1835
b1011011 !
#1840
b10100100 "
#1845
0%
#1850
1%
#1855
b1011100 !
#1860
b10100011 "
#1865
0%
#1870
1%
#1875
b1011101 !
#1880
b10100010 "
#1885
0%
#1890
1%
#1895
b1011110 !
#1900
b10100001 "
#1905
0%
#1910
1%
#1915
b1011111 !
#1920
b10100000 "
#1925
0%
#1930
1%
#1935
b1100000 !
#1940
b10011111 "
#1945
0%
#1950
1%
#1955
b1100001 !
#1960
b10011110 "
#1965
0%
#1970
1%
#1975
b1100010 !
#1980
b10011101 "
#1985
0%
#1990
1%
#1995
b1100011 !
#2000
b10011100 "
#2005
0%
#2010
1%
#2015
b1100100 !
#2020
b10011011 "
#2025
0%
#2030
1%
#2035
b1100101 !
#2040
b10011010 "
#2045
0%
#2050
1%
#2055
b1100110 !
#2060
b10011001 "
#2065
0%
#2070
1%
#2075
b1100111 !
#2080
b10011000 "
#2085
0%
#2090
1%
#2095
b1101000 !
#2100
b10010111 "
#2105
0%
#2110
1%
#2115
b1101001 !
#2120
b10010110 "
#2125
0%
#2130
1%
#2135
b1101010 !
#2140
b10010101 "
#2145
0%
#2150
1%
#2155
b1101011 !
#2160
b10010100 "
#2165
0%
#2170
1%
#2175
b1101100 !
#2180
b10010011 "
#2185
0%
#2190
1%
#2195
b1101101 !
#2200
b10010010 "
#2205
0%
#2210
1%
#2215
b1101110 !
#2220
b10010001 "
#2225
0%
#2230
1%
#2235
b1101111 !
#2240
b10010000 "
#2245
0%
#2250
1%
#2255
b1110000 !
#2260
b10001111 "
#2265
0%
#2270
1%
#2275
b1110001 !
#2280
b10001110 "
#2285
0%
#2290
1%
#2295
b1110010 !
#2300
b10001101 "
#2305
0%
#2310
1%
#2315
b1110011 !
#2320
b10001100 "
#2325
0%
#2330
1%
#2335
b1110100 !
#2340
b10001011 "
#2345
0%
#2350
1%
#2355
b1110101 !
#2360
b10001010 "
#2365
0%
#2370
1%
#2375
b1110110 !
#2380
b10001001 "
#2385
0%
#2390
1%
#2395
b1110111 !
#2400
b10001000 "
#2405
0%
#2410
1%
#2415
b1111000 !
#2420
b10000111 "
#2425
0%
#2430
1%
#2435
b1111001 !
#2440
b10000110 "
#2445
0%
#2450
1%
#2455
b1111010 !
#2460
b10000101 "
#2465
0%
#2470
1%
#2475
b1111011 !
#2480
b10000100 "
#2485
0%
#2490
1%
#2495
b1111100 !
#2500
b10000011 "
#2505
0%
#2510
1%
#2515
b1111101 !
#2520
b10000010 "
#2525
0%
#2530
1%
#2535
b1111110 !
#2540
b10000001 "
#2545
0%
#2550
1%
#2555
b1111111 !
#2560
b10000000 "
#2565
0%
#2570
1%
#2575
b10000000 !
#2580
b1111111 "
#2585
0%
#2590
1%
#2595
b10000001 !
#2600
b1111110 "
#2605
0%
#2610
1%
#2615
b10000010 !
#2620
b1111101 "
#2625
0%
#2630
1%
#2635
b10000011 !
#2640
b1111100 "
#2645
0%
#2650
1%
#2655
b10000100 !
#2660
b1111011 "
#2665
0%
#2670
1%
#2675
b10000101 !
#2680
b1111010 "
#2685
0%
#2690
1%
#2695
b10000110 !
#2700
b1111001 "
#2705
0%
#2710
1%
#2715
b10000111 !
#2720
b1111000 "
#2725
0%
#2730
1%
#2735
b10001000 !
#2740
b1110111 "
#2745
0%
#2750
1%
#2755
b10001001 !
#2760
b1110110 "
#2765
0%
#2770
1%
#2775
b10001010 !
#2780
b1110101 "
#2785
0%
#2790
1%
#2795
b10001011 !
#2800
b1110100 "
#2805
0%
#2810
1%
#2815
b10001100 !
#2820
b1110011 "
#2825
0%
#2830
1%
#2835
b10001101 !
#2840
b1110010 "
#2845
0%
#2850
1%
#2855
b10001110 !
#2860
b1110001 "
#2865
0%
#2870
1%
#2875
b10001111 !
#2880
b1110000 "
#2885
0%
#2890
1%
#2895
b10010000 !
#2900
b1101111 "
#2905
0%
#2910
1%
#2915
b10010001 !
#2920
b1101110 "
#2925
0%
#2930
1%
#2935
b10010010 !
#2940
b1101101 "
#2945
0%
#2950
1%
#2955
b10010011 !
#2960
b1101100 "
#2965
0%
#2970
1%
#2975
b10010100 !
#2980
b1101011 "
#2985
0%
#2990
1%
#2995
b10010101 !
#3000
b1101010 "
#3005
0%
#3010
1%
#3015
b10010110 !
#3020
b1101001 "
#3025
0%
#3030
1%
#3035
b10010111 !
#3040
b1101000 "
#3045
0%
#3050
1%
#3055
b10011000 !
#3060
b1100111 "
#3065
0%
#3070
1%
#3075
b10011001 !
#3080
b1100110 "
#3085
0%
#3090
1%
#3095
b10011010 !
#3100
b1100101 "
#3105
0%
#3110
1%
#3115
b10011011 !
#3120
b1100100 "
#3125
0%
#3130
1%
#3135
b10011100 !
#3140
b1100011 "
#3145
0%
#3150
1%
#3155
b10011101 !
#3160
b1100010 "
#3165
0%
#3170
1%
#3175
b10011110 !
#3180
b1100001 "
#3185
0%
#3190
1%
#3195
b10011111 !
#3200
b1100000 "
#3205
0%
#3210
1%
#3215
b10100000 !
#3220
b1011111 "
#3225
0%
#3230
1%
#3235
b10100001 !
#3240
b1011110 "
#3245
0%
#3250
1%
#3255
b10100010 !
#3260
b1011101 "
#3265
0%
#3270
1%
#3275
b10100011 !
#3280
b1011100 "
#3285
0%
#3290
1%
#3295
b10100100 !
#3300
b1011011 "
#3305
0%
#3310
1%
#3315
b10100101 !
#3320
b1011010 "
#3325
0%
#3330
1%
#3335
b10100110 !
#3340
b1011001 "
#3345
0%
#3350
1%
#3355
b10100111 !
#3360
b1011000 "
#3365
0%
#3370
1%
#3375
b10101000 !
#3380
b1010111 "
#3385
0%
#3390
1%
#3395
b10101001 !
#3400
b1010110 "
#3405
0%
#3410
1%
#3415
b10101010 !
#3420
b1010101 "
#3425
0%
#3430
1%
#3435
b10101011 !
#3440
b1010100 "
#3445
0%
#3450
1%
#3455
b10101100 !
#3460
b1010011 "
#3465
0%
#3470
1%
#3475
b10101101 !
#3480
b1010010 "
#3485
0%
#3490
1%
#3495
b10101110 !
#3500
b1010001 "
#3505
0%
#3510
1%
#3515
b10101111 !
#3520
b1010000 "
#3525
0%
#3530
1%
#3535
b10110000 !
#3540
b1001111 "
#3545
0%
#3550
1%
#3555
b10110001 !
#3560
b1001110 "
#3565
0%
#3570
1%
#3575
b10110010 !
#3580
b1001101 "
#3585
0%
#3590
1%
#3595
b10110011 !
#3600
b1001100 "
#3605
0%
#3610
1%
#3615
b10110100 !
#3620
b1001011 "
#3625
0%
#3630
1%
#3635
b10110101 !
#3640
b1001010 "
#3645
0%
#3650
1%
#3655
b10110110 !
#3660
b1001001 "
#3665
0%
#3670
1%
#3675
b10110111 !
#3680
b1001000 "
#3685
0%
#3690
1%
#3695
b10111000 !
#3700
b1000111 "
#3705
0%
#3710
1%
#3715
b10111001 !
#3720
b1000110 "
#3725
0%
#3730
1%
#3735
b10111010 !
#3740
b1000101 "
#3745
0%
#3750
1%
#3755
b10111011 !
#3760
b1000100 "
#3765
0%
#3770
1%
#3775
b10111100 !
#3780
b1000011 "
#3785
0%
#3790
1%
#3795
b10111101 !
#3800
b1000010 "
#3805
0%
#3810
1%
#3815
b10111110 !
#3820
b1000001 "
#3825
0%
#3830
1%
#3835
b10111111 !
#3840
b1000000 "
#3845
0%
#3850
1%
#3855
b11000000 !
#3860
b111111 "
#3865
0%
#3870
1%
#3875
b11000001 !
#3880
b111110 "
#3885
0%
#3890
1%
#3895
b11000010 !
#3900
b111101 "
#3905
0%
#3910
1%
#3915
b11000011 !
#3920
b111100 "
#3925
0%
#3930
1%
#3935
b11000100 !
#3940
b111011 "
#3945
0%
#3950
1%
#3955
b11000101 !
#3960
b111010 "
#3965
0%
#3970
1%
#3975
b11000110 !
#3980
b111001 "
#3985
0%
#3990
1%
#3995
b11000111 !
#4000
b111000 "
#4005
0%
#4010
1%
#4015
b11001000 !
#4020
b110111 "
#4025
0%
#4030
1%
#4035
b11001001 !
#4040
b110110 "
#4045
0%
#4050
1%
#4055
b11001010 !
#4060
b110101 "
#4065
0%
#4070
1%
#4075
b11001011 !
#4080
b110100 "
#4085
0%
#4090
1%
#4095
b11001100 !
#4100
b110011 "
#4105
0%
#4110
1%
#4115
b11001101 !
#4120
b110010 "
#4125
0%
#4130
1%
#4135
b11001110 !
#4140
b110001 "
#4145
0%
#4150
1%
#4155
b11001111 !
#4160
b110000 "
#4165
0%
#4170
1%
#4175
b11010000 !
#4180
b101111 "
#4185
0%
#4190
1%
#4195
b11010001 !
#4200
b101110 "
#4205
0%
#4210
1%
#4215
b11010010 !
#4220
b101101 "
#4225
0%
#4230
1%
#4235
b11010011 !
#4240
b101100 "
#4245
0%
#4250
1%
#4255
b11010100 !
#4260
b101011 "
#4265
0%
#4270
1%
#4275
b11010101 !
#4280
b101010 "
#4285
0%
#4290
1%
#4295
b11010110 !
#4300
b101001 "
#4305
0%
#4310
1%
#4315
b11010111 !
#4320
b101000 "
#4325
0%
#4330
1%
#4335
b11011000 !
#4340
b100111 "
#4345
0%
#4350
1%
#4355
b11011001 !
#4360
b100110 "
#4365
0%
#4370
1%
#4375
b11011010 !
#4380
b100101 "
#4385
0%
#4390
1%
#4395
b11011011 !
#4400
b100100 "
#4405
0%
#4410
1%
#4415
b11011100 !
#4420
b100011 "
#4425
0%
#4430
1%
#4435
b11011101 !
#4440
b100010 "
#4445
0%
#4450
1%
#4455
b11011110 !
#4460
b100001 "
#4465
0%
#4470
1%
#4475
b11011111 !
#4480
b100000 "
#4485
0%
#4490
1%
#4495
b11100000 !
#4500
b11111 "
#4505
0%
#4510
1%
#4515
b11100001 !
#4520
b11110 "
#4525
0%
#4530
1%
#4535
b11100010 !
#4540
b11101 "
#4545
0%
#4550
1%
#4555
b11100011 !
#4560
b11100 "
#4565
0%
#4570
1%
#4575
b11100100 !
#4580
b11011 "
#4585
0%
#4590
1%
#4595
b11100101 !
#4600
b11010 "
#4605
0%
#4610
1%
#4615
b11100110 !
#4620
b11001 "
#4625
0%
#4630
1%
#4635
b11100111 !
#4640
b11000 "
#4645
0%
#4650
1%
#4655
b11101000 !
#4660
b10111 "
#4665
0%
#4670
1%
#4675
b11101001 !
#4680
b10110 "
#4685
0%
#4690
1%
#4695
b11101010 !
#4700
b10101 "
#4705
0%
#4710
1%
#4715
b11101011 !
#4720
b10100 "
#4725
0%
#4730
1%
#4735
b11101100 !
#4740
b10011 "
#4745
0%
#4750
1%
#4755
b11101101 !
#4760
b10010 "
#4765
0%
#4770
1%
#4775
b11101110 !
#4780
b10001 "
#4785
0%
#4790
1%
#4795
b11101111 !
#4800
b10000 "
#4805
0%
#4810
1%
#4815
b11110000 !
#4820
b1111 "
#4825
0%
#4830
1%
#4835
b11110001 !
#4840
b1110 "
#4845
0%
#4850
1%
#4855
b11110010 !
#4860
b1101 "
#4865
0%
#4870
1%
#4875
b11110011 !
#4880
b1100 "
#4885
0%
#4890
1%
#4895
b11110100 !
#4900
b1011 "
#4905
0%
#4910
1%
#4915
b11110101 !
#4920
b1010 "
#4925
0%
#4930
1%
#4935
b11110110 !
#4940
b1001 "
#4945
0%
#4950
1%
#4955
b11110111 !
#4960
b1000 "
#4965
0%
#4970
1%
#4975
b11111000 !
#4980
b111 "
#4985
0%
#4990
1%
#4995
b11111001 !
#5000
b110 "
#5005
0%
#5010
1%
#5015
b11111010 !
#5020
b101 "
#5025
0%
#5030
1%
#5035
b11111011 !
#5040
b100 "
#5045
0%
#5050
1%
#5055
b11111100 !
#5060
b11 "
#5065
0%
#5070
1%
#5075
b11111101 !
#5080
b10 "
#5085
0%
#5090
1%
#5095
b11111110 !
#5100
b1 "
#5105
0%
#5110
1%
#5115
b11111111 !
#5120
b0 "
#5125
0%
#5130
b0 "
0$
1%
#5135
b11111111 "
b0 !
#5150
b0 "
1$
#5155
b11111111 "
0$
#5160
b11111110 "
b1 !
#5175
b0 "
1$
#5180
b11111110 "
0$
#5185
b11111101 "
b10 !
#5200
b0 "
1$
#5205
b11111101 "
0$
#5210
b11111100 "
b11 !
#5225
b0 "
1$
#5230
b11111100 "
0$
#5235
b11111011 "
b100 !
#5250
b0 "
1$
#5255
b11111011 "
0$
#5260
b11111010 "
b101 !
#5275
b0 "
1$
#5280
b11111010 "
0$
#5285
b11111001 "
b110 !
#5300
b0 "
1$
#5305
b11111001 "
0$
#5310
b11111000 "
b111 !
#5325
b0 "
1$
#5330
b11111000 "
0$
#5335
b11110111 "
b1000 !
#5350
b0 "
1$
#5355
b11110111 "
0$
#5360
b11110110 "
b1001 !
#5375
b0 "
1$
#5380
b11110110 "
0$
#5385
b11110101 "
b1010 !
#5400
b0 "
1$
#5405
b11110101 "
0$
#5410
b11110100 "
b1011 !
#5425
b0 "
1$
#5430
b11110100 "
0$
#5435
b11110011 "
b1100 !
#5450
b0 "
1$
#5455
b11110011 "
0$
#5460
b11110010 "
b1101 !
#5475
b0 "
1$
#5480
b11110010 "
0$
#5485
b11110001 "
b1110 !
#5500
b0 "
1$
#5505
b11110001 "
0$
#5510
b11110000 "
b1111 !
#5525
b0 "
1$
#5530
b11110000 "
0$
#5535
b11101111 "
b10000 !
#5550
b0 "
1$
#5555
b11101111 "
0$
#5560
b11101110 "
b10001 !
#5575
b0 "
1$
#5580
b11101110 "
0$
#5585
b11101101 "
b10010 !
#5600
b0 "
1$
#5605
b11101101 "
0$
#5610
b11101100 "
b10011 !
#5625
b0 "
1$
#5630
b11101100 "
0$
#5635
b11101011 "
b10100 !
#5650
b0 "
1$
#5655
b11101011 "
0$
#5660
b11101010 "
b10101 !
#5675
b0 "
1$
#5680
b11101010 "
0$
#5685
b11101001 "
b10110 !
#5700
b0 "
1$
#5705
b11101001 "
0$
#5710
b11101000 "
b10111 !
#5725
b0 "
1$
#5730
b11101000 "
0$
#5735
b11100111 "
b11000 !
#5750
b0 "
1$
#5755
b11100111 "
0$
#5760
b11100110 "
b11001 !
#5775
b0 "
1$
#5780
b11100110 "
0$
#5785
b11100101 "
b11010 !
#5800
b0 "
1$
#5805
b11100101 "
0$
#5810
b11100100 "
b11011 !
#5825
b0 "
1$
#5830
b11100100 "
0$
#5835
b11100011 "
b11100 !
#5850
b0 "
1$
#5855
b11100011 "
0$
#5860
b11100010 "
b11101 !
#5875
b0 "
1$
#5880
b11100010 "
0$
#5885
b11100001 "
b11110 !
#5900
b0 "
1$
#5905
b11100001 "
0$
#5910
b11100000 "
b11111 !
#5925
b0 "
1$
#5930
b11100000 "
0$
#5935
b11011111 "
b100000 !
#5950
b0 "
1$
#5955
b11011111 "
0$
#5960
b11011110 "
b100001 !
#5975
b0 "
1$
#5980
b11011110 "
0$
#5985
b11011101 "
b100010 !
#6000
b0 "
1$
#6005
b11011101 "
0$
#6010
b11011100 "
b100011 !
#6025
b0 "
1$
#6030
b11011100 "
0$
#6035
b11011011 "
b100100 !
#6050
b0 "
1$
#6055
b11011011 "
0$
#6060
b11011010 "
b100101 !
#6075
b0 "
1$
#6080
b11011010 "
0$
#6085
b11011001 "
b100110 !
#6100
b0 "
1$
#6105
b11011001 "
0$
#6110
b11011000 "
b100111 !
#6125
b0 "
1$
#6130
b11011000 "
0$
#6135
b11010111 "
b101000 !
#6150
b0 "
1$
#6155
b11010111 "
0$
#6160
b11010110 "
b101001 !
#6175
b0 "
1$
#6180
b11010110 "
0$
#6185
b11010101 "
b101010 !
#6200
b0 "
1$
#6205
b11010101 "
0$
#6210
b11010100 "
b101011 !
#6225
b0 "
1$
#6230
b11010100 "
0$
#6235
b11010011 "
b101100 !
#6250
b0 "
1$
#6255
b11010011 "
0$
#6260
b11010010 "
b101101 !
#6275
b0 "
1$
#6280
b11010010 "
0$
#6285
b11010001 "
b101110 !
#6300
b0 "
1$
#6305
b11010001 "
0$
#6310
b11010000 "
b101111 !
#6325
b0 "
1$
#6330
b11010000 "
0$
#6335
b11001111 "
b110000 !
#6350
b0 "
1$
#6355
b11001111 "
0$
#6360
b11001110 "
b110001 !
#6375
b0 "
1$
#6380
b11001110 "
0$
#6385
b11001101 "
b110010 !
#6400
b0 "
1$
#6405
b11001101 "
0$
#6410
b11001100 "
b110011 !
#6425
b0 "
1$
#6430
b11001100 "
0$
#6435
b11001011 "
b110100 !
#6450
b0 "
1$
#6455
b11001011 "
0$
#6460
b11001010 "
b110101 !
#6475
b0 "
1$
#6480
b11001010 "
0$
#6485
b11001001 "
b110110 !
#6500
b0 "
1$
#6505
b11001001 "
0$
#6510
b11001000 "
b110111 !
#6525
b0 "
1$
#6530
b11001000 "
0$
#6535
b11000111 "
b111000 !
#6550
b0 "
1$
#6555
b11000111 "
0$
#6560
b11000110 "
b111001 !
#6575
b0 "
1$
#6580
b11000110 "
0$
#6585
b11000101 "
b111010 !
#6600
b0 "
1$
#6605
b11000101 "
0$
#6610
b11000100 "
b111011 !
#6625
b0 "
1$
#6630
b11000100 "
0$
#6635
b11000011 "
b111100 !
#6650
b0 "
1$
#6655
b11000011 "
0$
#6660
b11000010 "
b111101 !
#6675
b0 "
1$
#6680
b11000010 "
0$
#6685
b11000001 "
b111110 !
#6700
b0 "
1$
#6705
b11000001 "
0$
#6710
b11000000 "
b111111 !
#6725
b0 "
1$
#6730
b11000000 "
0$
#6735
b10111111 "
b1000000 !
#6750
b0 "
1$
#6755
b10111111 "
0$
#6760
b10111110 "
b1000001 !
#6775
b0 "
1$
#6780
b10111110 "
0$
#6785
b10111101 "
b1000010 !
#6800
b0 "
1$
#6805
b10111101 "
0$
#6810
b10111100 "
b1000011 !
#6825
b0 "
1$
#6830
b10111100 "
0$
#6835
b10111011 "
b1000100 !
#6850
b0 "
1$
#6855
b10111011 "
0$
#6860
b10111010 "
b1000101 !
#6875
b0 "
1$
#6880
b10111010 "
0$
#6885
b10111001 "
b1000110 !
#6900
b0 "
1$
#6905
b10111001 "
0$
#6910
b10111000 "
b1000111 !
#6925
b0 "
1$
#6930
b10111000 "
0$
#6935
b10110111 "
b1001000 !
#6950
b0 "
1$
#6955
b10110111 "
0$
#6960
b10110110 "
b1001001 !
#6975
b0 "
1$
#6980
b10110110 "
0$
#6985
b10110101 "
b1001010 !
#7000
b0 "
1$
#7005
b10110101 "
0$
#7010
b10110100 "
b1001011 !
#7025
b0 "
1$
#7030
b10110100 "
0$
#7035
b10110011 "
b1001100 !
#7050
b0 "
1$
#7055
b10110011 "
0$
#7060
b10110010 "
b1001101 !
#7075
b0 "
1$
#7080
b10110010 "
0$
#7085
b10110001 "
b1001110 !
#7100
b0 "
1$
#7105
b10110001 "
0$
#7110
b10110000 "
b1001111 !
#7125
b0 "
1$
#7130
b10110000 "
0$
#7135
b10101111 "
b1010000 !
#7150
b0 "
1$
#7155
b10101111 "
0$
#7160
b10101110 "
b1010001 !
#7175
b0 "
1$
#7180
b10101110 "
0$
#7185
b10101101 "
b1010010 !
#7200
b0 "
1$
#7205
b10101101 "
0$
#7210
b10101100 "
b1010011 !
#7225
b0 "
1$
#7230
b10101100 "
0$
#7235
b10101011 "
b1010100 !
#7250
b0 "
1$
#7255
b10101011 "
0$
#7260
b10101010 "
b1010101 !
#7275
b0 "
1$
#7280
b10101010 "
0$
#7285
b10101001 "
b1010110 !
#7300
b0 "
1$
#7305
b10101001 "
0$
#7310
b10101000 "
b1010111 !
#7325
b0 "
1$
#7330
b10101000 "
0$
#7335
b10100111 "
b1011000 !
#7350
b0 "
1$
#7355
b10100111 "
0$
#7360
b10100110 "
b1011001 !
#7375
b0 "
1$
#7380
b10100110 "
0$
#7385
b10100101 "
b1011010 !
#7400
b0 "
1$
#7405
b10100101 "
0$
#7410
b10100100 "
b1011011 !
#7425
b0 "
1$
#7430
b10100100 "
0$
#7435
b10100011 "
b1011100 !
#7450
b0 "
1$
#7455
b10100011 "
0$
#7460
b10100010 "
b1011101 !
#7475
b0 "
1$
#7480
b10100010 "
0$
#7485
b10100001 "
b1011110 !
#7500
b0 "
1$
#7505
b10100001 "
0$
#7510
b10100000 "
b1011111 !
#7525
b0 "
1$
#7530
b10100000 "
0$
#7535
b10011111 "
b1100000 !
#7550
b0 "
1$
#7555
b10011111 "
0$
#7560
b10011110 "
b1100001 !
#7575
b0 "
1$
